setup.py
testbz/__init__.py
testbz.egg-info/PKG-INFO
testbz.egg-info/SOURCES.txt
testbz.egg-info/dependency_links.txt
testbz.egg-info/not-zip-safe
testbz.egg-info/top_level.txt