Metadata-Version: 1.0
Name: testbz
Version: 0.1
Summary: testbz version
Home-page: http://github.com/baozun/testbz
Author: swiftay
Author-email: qianxunl13@163.com
License: MIT
Platform: UNKNOWN
